posty/__init__.py
posty/cli.py
posty/config.py
posty/exceptions.py
posty/importers.py
posty/model.py
posty/page.py
posty/post.py
posty/site.py
posty/util.py
posty/renderer/__init__.py
posty/renderer/atom.py
posty/renderer/base.py
posty/renderer/feed.py
posty/renderer/html.py
posty/renderer/json.py
posty/renderer/posty1_redirect.py
posty/renderer/rss.py
posty/renderer/util.py
posty/skel/config.yml
posty/skel/media/.keep
posty/skel/pages/.keep
posty/skel/pages/new-page.yaml
posty/skel/posts/.keep
posty/skel/posts/1970-01-01_new-post.yaml
posty/skel/templates/.keep
posty/skel/templates/redirect.html
posty-2.1.1.post1.dist-info/METADATA
posty-2.1.1.post1.dist-info/WHEEL
posty-2.1.1.post1.dist-info/entry_points.txt
posty-2.1.1.post1.dist-info/licenses/LICENSE
posty-2.1.1.post1.dist-info/RECORD
