Metadata-Version: 2.4
Name: posty
Version: 2.1.1.post1
Summary: A static site generator
Project-URL: Source, https://github.com/nickpegg/posty
Project-URL: Documentation, https://posty.readthedocs.io
Author-email: Nick Pegg <nick@nickpegg.com>
License-Expression: MIT
License-File: LICENSE
Requires-Python: >=3.10
Requires-Dist: awesome-slugify~=1.6
Requires-Dist: click<9,>=7
Requires-Dist: feedgen<1.1,>=0.9
Requires-Dist: jinja2~=3.1
Requires-Dist: markdown~=3.3
Requires-Dist: pytz
Requires-Dist: pyyaml
Provides-Extra: docs
Requires-Dist: sphinx; extra == 'docs'
Requires-Dist: sphinx-click; extra == 'docs'
Requires-Dist: sphinx-rtd-theme; extra == 'docs'
